{
    "created": 1627939168,
    "updated": 1775098935,
    "created_date": "2021-08-02T21:19:28Z",
    "updated_date": "2026-04-02T03:02:15Z",
    "active": "1",
    "title": "Current Daily Price of Various Commodities from Various Markets (Mandi)",
    "source": "data.gov.in",
    "desc": "Current Daily Price of Various Commodities from Various Markets (Mandi)",
    "records": [
        {
            "state": "Tamil Nadu",
            "district": "Dharmapuri",
            "market": "Karimangalam(Uzhavar Sandhai)",
            "commodity": "Brinjal",
            "variety": "Other",
            "grade": "Local",
            "arrival_date": "02/04/2026",
            "min_price": 2000,
            "max_price": 2500,
            "modal_price": 2250
        },
        {
            "state": "Tamil Nadu",
            "district": "Dharmapuri",
            "market": "Karimangalam(Uzhavar Sandhai)",
            "commodity": "Green Peas",
            "variety": "Green Peas",
            "grade": "Local",
            "arrival_date": "02/04/2026",
            "min_price": 9500,
            "max_price": 10000,
            "modal_price": 9750
        },
        {
            "state": "Tamil Nadu",
            "district": "Dharmapuri",
            "market": "Karimangalam(Uzhavar Sandhai)",
            "commodity": "Cluster beans",
            "variety": "Cluster Beans",
            "grade": "Local",
            "arrival_date": "02/04/2026",
            "min_price": 3800,
            "max_price": 4000,
            "modal_price": 3900
        },
        {
            "state": "Tamil Nadu",
            "district": "Dharmapuri",
            "market": "Karimangalam(Uzhavar Sandhai)",
            "commodity": "Beans",
            "variety": "Beans (Whole)",
            "grade": "Local",
            "arrival_date": "02/04/2026",
            "min_price": 7500,
            "max_price": 8000,
            "modal_price": 7750
        },
        {
            "state": "Tamil Nadu",
            "district": "Dharmapuri",
            "market": "Karimangalam(Uzhavar Sandhai)",
            "commodity": "Raddish",
            "variety": "Raddish",
            "grade": "Local",
            "arrival_date": "02/04/2026",
            "min_price": 1200,
            "max_price": 1500,
            "modal_price": 1350
        },
        {
            "state": "Tamil Nadu",
            "district": "Salem",
            "market": "Mecheri(Uzhavar Sandhai)",
            "commodity": "Garlic",
            "variety": "Garlic",
            "grade": "Local",
            "arrival_date": "02/04/2026",
            "min_price": 12000,
            "max_price": 13000,
            "modal_price": 12500
        },
        {
            "state": "Tamil Nadu",
            "district": "Salem",
            "market": "Mecheri(Uzhavar Sandhai)",
            "commodity": "Coriander(Leaves)",
            "variety": "I Sort",
            "grade": "Local",
            "arrival_date": "02/04/2026",
            "min_price": 1800,
            "max_price": 2000,
            "modal_price": 1900
        },
        {
            "state": "Madhya Pradesh",
            "district": "Sagar",
            "market": "Sagar APMC",
            "commodity": "Soyabean",
            "variety": "Soyabeen",
            "grade": "FAQ",
            "arrival_date": "02/04/2026",
            "min_price": 4800,
            "max_price": 4805,
            "modal_price": 4805
        },
        {
            "state": "Odisha",
            "district": "Sundergarh",
            "market": "Panposh APMC",
            "commodity": "Cabbage",
            "variety": "Cabbage",
            "grade": "FAQ",
            "arrival_date": "02/04/2026",
            "min_price": 2000,
            "max_price": 3000,
            "modal_price": 2500
        },
        {
            "state": "Haryana",
            "district": "Gurgaon",
            "market": "Gurgaon APMC",
            "commodity": "Potato",
            "variety": "Other",
            "grade": "Grade B",
            "arrival_date": "02/04/2026",
            "min_price": 500,
            "max_price": 700,
            "modal_price": 600
        },
        {
            "state": "Jammu and Kashmir",
            "district": "Kathua",
            "market": "Kathua APMC",
            "commodity": "Tomato",
            "variety": "Other",
            "grade": "FAQ",
            "arrival_date": "02/04/2026",
            "min_price": 1700,
            "max_price": 2000,
            "modal_price": 1850
        },
        {
            "state": "Punjab",
            "district": "Bhatinda",
            "market": "Rampuraphul(Nabha Mandi) APMC",
            "commodity": "Apple",
            "variety": "Other",
            "grade": "Grade A",
            "arrival_date": "02/04/2026",
            "min_price": 8000,
            "max_price": 10000,
            "modal_price": 9000
        }
    ]
}
